digpy/__init__.py
digpy/weather.py
digpy-0.0.1.dist-info/METADATA
digpy-0.0.1.dist-info/WHEEL
digpy-0.0.1.dist-info/licenses/LICENSE
digpy-0.0.1.dist-info/RECORD
